wcpan/drive/crypt/__init__.py
wcpan/drive/crypt/_lib.py
wcpan/drive/crypt/_service.py
wcpan/drive/crypt/py.typed
wcpan_drive_crypt-4.1.1.dist-info/LICENSE.txt
wcpan_drive_crypt-4.1.1.dist-info/METADATA
wcpan_drive_crypt-4.1.1.dist-info/WHEEL
wcpan_drive_crypt-4.1.1.dist-info/RECORD
